membrain_memtrain/__init__.py
membrain_memtrain/core/__init__.py
membrain_memtrain-0.0.1.dist-info/LICENSE
membrain_memtrain-0.0.1.dist-info/METADATA
membrain_memtrain-0.0.1.dist-info/WHEEL
membrain_memtrain-0.0.1.dist-info/RECORD
