Metadata-Version: 2.3
Name: membrain-memtrain
Version: 0.0.1
Summary: MemBrain-MemTrain
License: Apache-2.0
Author: Rohit Garud
Requires-Python: >=3.10
Classifier: License :: OSI Approved :: Apache Software License
Classifier: Programming Language :: Python :: 3
Classifier: Programming Language :: Python :: 3.10
Classifier: Programming Language :: Python :: 3.11
Classifier: Programming Language :: Python :: 3.12
Classifier: Programming Language :: Python :: 3.13
